README.md
pyproject.toml
setup.py
live_client/__init__.py
live_client/facades.py
live_client.egg-info/PKG-INFO
live_client.egg-info/SOURCES.txt
live_client.egg-info/dependency_links.txt
live_client.egg-info/requires.txt
live_client.egg-info/top_level.txt
live_client.egg-info/zip-safe
live_client/assets/__init__.py
live_client/assets/assets.py
live_client/assets/auto_analysis.py
live_client/assets/curves.py
live_client/connection/__init__.py
live_client/connection/autodetect.py
live_client/connection/rest_input.py
live_client/connection/tcp_input.py
live_client/events/__init__.py
live_client/events/annotation.py
live_client/events/constants.py
live_client/events/debug.py
live_client/events/messenger.py
live_client/events/raw.py
live_client/query/__init__.py
live_client/query/query.py
live_client/resources/__init__.py
live_client/resources/base.py
live_client/resources/dashboards.py
live_client/resources/messenger.py
live_client/resources/plugins.py
live_client/resources/access_control/__init__.py
live_client/resources/access_control/permissions.py
live_client/resources/access_control/role.py
live_client/resources/access_control/team.py
live_client/resources/access_control/user.py
live_client/scripts/check-live-features
live_client/types/__init__.py
live_client/types/message.py
live_client/utils/__init__.py
live_client/utils/colors.py
live_client/utils/features.py
live_client/utils/http.py
live_client/utils/logging.py
live_client/utils/network.py
live_client/utils/processes.py
live_client/utils/timestamp.py
test/test_events_messenger.py
test/test_events_raw.py
test/testbase.py