Metadata-Version: 2.1
Name: live-client
Version: 0.8.1
Summary: Client libraries to connect with the Intelie LIVE platform
Home-page: https://github.com/intelie/liveclient-python
Author: Vitor Mazzi
Author-email: vitor.mazzi@intelie.com.br
License: UNKNOWN
Platform: UNKNOWN
Classifier: Programming Language :: Python :: 3
Classifier: License :: OSI Approved :: GNU General Public License v3 (GPLv3)
Classifier: Operating System :: OS Independent
Classifier: Development Status :: 4 - Beta
Classifier: Topic :: Scientific/Engineering
Classifier: Topic :: System :: Monitoring
Requires-Python: >=3.6
